docs/source/conf.py
pyspedas/__init__.py
pyspedas/version.py
pyspedas/analysis/README.md
pyspedas/analysis/__init__.py
pyspedas/analysis/avg_data.py
pyspedas/analysis/deriv_data.py
pyspedas/analysis/find_magnetic_nulls.py
pyspedas/analysis/interp_gap.py
pyspedas/analysis/lingradest.py
pyspedas/analysis/neutral_sheet.py
pyspedas/analysis/rebin.py
pyspedas/analysis/reduce_tres.py
pyspedas/analysis/roundsig.py
pyspedas/analysis/time_domain_filter.py
pyspedas/analysis/tinterpol.py
pyspedas/analysis/tvectot.py
pyspedas/analysis/twavpol.py
pyspedas/analysis/wav_data.py
pyspedas/analysis/wave_signif.py
pyspedas/analysis/wavelet.py
pyspedas/analysis/wavelet2.py
pyspedas/analysis/wavelet98.py
pyspedas/analysis/yclip.py
pyspedas/analysis/tests/__init__.py
pyspedas/analysis/tests/test_analysis.py
pyspedas/analysis/tests/test_magnetic_nulls.py
pyspedas/analysis/tests/test_twavpol.py
pyspedas/analysis/tests/test_wavelet.py
pyspedas/analysis/tests/wavetest.py
pyspedas/cdagui_tools/__init__.py
pyspedas/cdagui_tools/cdagui.py
pyspedas/cdagui_tools/cdaweb.py
pyspedas/cdagui_tools/config.py
pyspedas/cdagui_tools/tests/__init__.py
pyspedas/cdagui_tools/tests/test_cdagui.py
pyspedas/cotrans_tools/__init__.py
pyspedas/cotrans_tools/cart2spc.py
pyspedas/cotrans_tools/cart_to_sphere.py
pyspedas/cotrans_tools/cotrans.py
pyspedas/cotrans_tools/cotrans_lib.py
pyspedas/cotrans_tools/fac_matrix_make.py
pyspedas/cotrans_tools/gsm2lmn.py
pyspedas/cotrans_tools/igrf.py
pyspedas/cotrans_tools/j2000.py
pyspedas/cotrans_tools/lmn_matrix_make.py
pyspedas/cotrans_tools/matrix_array_lib.py
pyspedas/cotrans_tools/minvar.py
pyspedas/cotrans_tools/minvar_matrix_make.py
pyspedas/cotrans_tools/quaternions.py
pyspedas/cotrans_tools/rotmat_get_coords.py
pyspedas/cotrans_tools/rotmat_set_coords.py
pyspedas/cotrans_tools/sm2mlt.py
pyspedas/cotrans_tools/spc2cart.py
pyspedas/cotrans_tools/sphere_to_cart.py
pyspedas/cotrans_tools/tvector_rotate.py
pyspedas/cotrans_tools/xyz_to_polar.py
pyspedas-2.0.7.dist-info/licenses/LICENSE.txt
pyspedas-2.0.7.dist-info/METADATA
pyspedas-2.0.7.dist-info/WHEEL
pyspedas-2.0.7.dist-info/top_level.txt
pyspedas-2.0.7.dist-info/RECORD
