Metadata-Version: 2.4
Name: pyspedas
Version: 2.0.7
Summary: Python Space Physics Environment Data Analysis Software (pySPEDAS)
Author-email: Jim Lewis <jwl@ssl.berkeley.edu>
License-Expression: MIT
Project-URL: Homepage, https://github.com/spedas/pyspedas
Project-URL: Information, https://spedas.org/wiki/
Project-URL: Documentation, https://pyspedas.readthedocs.io
Project-URL: Issue_Tracker, https://github.com/spedas/pyspedas/issues
Project-URL: Source_Code, https://github.com/spedas/pyspedas
Project-URL: Concept_DOI, https://doi.org/10.5281/zenodo.17634923
Project-URL: Versioned_DOI, https://doi.org/10.5281/zenodo.18426486
Keywords: SPEDAS,data,tools,space physics,data analysis,space science,scientific computing,time series analysis,data visualization,satellite data,magnetosphere,ionosphere,heliophysics,geophysics,remote sensing,astrophysics,solar physics,space weather,data retrieval,NASA,NOAA,ESA,JAXA,HSO,CDF,ISTP,netCDF,Python package,THEMIS,ARTEMIS,MMS,ERG,Arase,ACE,MAVEN,RBSP,Van Allen Probes,GOES,POES,Cluster,OMNIWeb,aurora,geomagnetic index,Kp index,AE index,magnetic field models,Tsyganenko,IGRF,geopack,magn
Classifier: Development Status :: 5 - Production/Stable
Classifier: Intended Audience :: Science/Research
Classifier: Topic :: Scientific/Engineering
Classifier: Topic :: Scientific/Engineering :: Physics
Classifier: Topic :: Scientific/Engineering :: Astronomy
Classifier: Programming Language :: Python :: 3
Classifier: Programming Language :: Python :: 3.10
Classifier: Programming Language :: Python :: 3.11
Classifier: Programming Language :: Python :: 3.12
Classifier: Programming Language :: Python :: 3.13
Classifier: Programming Language :: Python :: 3.14
Classifier: Operating System :: OS Independent
Requires-Python: >=3.10
License-File: LICENSE.txt
Requires-Dist: numpy>=1.20.0
Requires-Dist: requests>=2.31.0
Requires-Dist: geopack>=1.0.12
Requires-Dist: scipy>=1.11.1
Requires-Dist: cdflib>=1.0.0
Requires-Dist: spacepy>=0.5.0
Requires-Dist: cdasws>=1.7.24
Requires-Dist: netCDF4>=1.6.2
Requires-Dist: pywavelets>=1.4.1
Requires-Dist: astropy>=5.3.1
Requires-Dist: hapiclient>=0.2.2
Requires-Dist: fsspec>=2023.9.0
Requires-Dist: s3fs>=2023.9.0
Requires-Dist: aioboto3>=11.1.1
Requires-Dist: pandas>=2.0.3
Requires-Dist: matplotlib>=3.6.2
Requires-Dist: xarray>=2023.7.0
Provides-Extra: mth5
Requires-Dist: mth5<0.6.0,>=0.5.0; extra == "mth5"
Requires-Dist: obspy>=1.4.2; extra == "mth5"
Requires-Dist: mt-metadata<1.0.0,>=0.4.0; extra == "mth5"
Provides-Extra: vires
Requires-Dist: viresclient>=0.13.0; extra == "vires"
Provides-Extra: maps
Requires-Dist: basemap>=2.0.0; extra == "maps"
Provides-Extra: all
Requires-Dist: mth5<0.6.0,>=0.5.0; extra == "all"
Requires-Dist: obspy>=1.4.2; extra == "all"
Requires-Dist: mt-metadata<1.0.0,>=0.4.0; extra == "all"
Requires-Dist: viresclient>=0.13.0; extra == "all"
Requires-Dist: basemap>=2.0.0; extra == "all"
Dynamic: license-file
